crankms/__init__.py
crankms/cls.py
crank_ms-0.0.1.dist-info/LICENSE
crank_ms-0.0.1.dist-info/METADATA
crank_ms-0.0.1.dist-info/WHEEL
crank_ms-0.0.1.dist-info/top_level.txt
crank_ms-0.0.1.dist-info/RECORD
